README.md
setup.cfg
setup.py
rodent/__init__.py
rodent/actions.py
rodent/licenses.py
rodent.egg-info/PKG-INFO
rodent.egg-info/SOURCES.txt
rodent.egg-info/dependency_links.txt
rodent.egg-info/not-zip-safe
rodent.egg-info/requires.txt
rodent.egg-info/top_level.txt
rodent/bin/rodent