Metadata-Version: 1.1
Name: rodent
Version: 0.1.1
Summary: A CLI utility to manage license headers
Home-page: https://github.com/mistercrunch/rodent
Author: Maxime Beauchemin
Author-email: maximebeauchemin@gmail.com
License: Apache License 2.0
Download-URL: https://github.com/mistercrunch/rodent/tarball/0.1.1
Platform: UNKNOWN
Classifier: Programming Language :: Python :: 2.7
Classifier: Programming Language :: Python :: 3.5
Classifier: Programming Language :: Python :: 3.6
Classifier: License :: OSI Approved :: Apache Software License
